smlb/__init__.py
smlb/core/__init__.py
smlb/core/data.py
smlb/core/distributions.py
smlb/core/evaluations.py
smlb/core/exceptions.py
smlb/core/features.py
smlb/core/java.py
smlb/core/learners.py
smlb/core/metrics.py
smlb/core/noise.py
smlb/core/object.py
smlb/core/optimizer.py
smlb/core/parameters.py
smlb/core/physchem.py
smlb/core/plots.py
smlb/core/random.py
smlb/core/sampling.py
smlb/core/scorer.py
smlb/core/tabular_data.py
smlb/core/transformations.py
smlb/core/utility.py
smlb/core/vector_space_data.py
smlb/core/workflow.py
smlb/datasets/__init__.py
smlb/datasets/experimental/__init__.py
smlb/datasets/experimental/band_gaps_sc73/__init__.py
smlb/datasets/experimental/band_gaps_sc73/band_gap_jpcrd_transformed-pif-onlyRef.json.zip
smlb/datasets/experimental/band_gaps_sc73/band_gaps_sc73.py
smlb/datasets/experimental/clean_energy_project/__init__.py
smlb/datasets/experimental/clean_energy_project/clean_energy_project.py
smlb/datasets/experimental/ni_superalloys/Ni_superalloy.py
smlb/datasets/experimental/ni_superalloys/__init__.py
smlb/datasets/experimental/ni_superalloys/ni_superalloys_3.json.zip
smlb/datasets/experimental/qm9_ramakrishnan_etal14/__init__.py
smlb/datasets/experimental/qm9_ramakrishnan_etal14/qm9_ramakrishnan_etal14.py
smlb/datasets/experimental/qm9_ramakrishnan_etal14/uncharacterized.txt
smlb/datasets/experimental/superconductors_citrine16/__init__.py
smlb/datasets/experimental/superconductors_citrine16/superconductors_citrine16.py
smlb/datasets/experimental/superconductors_citrine16/superconductors_transformed.csv
smlb/datasets/experimental/watercolor_pigments_c19/NTU_WPSM_dataset.zip
smlb/datasets/experimental/watercolor_pigments_c19/__init__.py
smlb/datasets/experimental/watercolor_pigments_c19/watercolor_pigments_c19.py
smlb/datasets/synthetic/__init__.py
smlb/datasets/synthetic/friedman_1979/__init__.py
smlb/datasets/synthetic/friedman_1979/friedman_1979.py
smlb/datasets/synthetic/friedman_silverman_1989/__init__.py
smlb-0.3.5.dist-info/LICENSE
smlb-0.3.5.dist-info/METADATA
smlb-0.3.5.dist-info/WHEEL
smlb-0.3.5.dist-info/top_level.txt
smlb-0.3.5.dist-info/RECORD
