Metadata-Version: 2.1
Name: smlb
Version: 0.3.5
Summary: Scientific Machine Learning Benchmark
Home-page: https://github.com/CitrineInformatics/smlb
Author: Matthias Rupp
Author-email: mrupp@mrupp.io
License: Apache-2.0
Platform: UNKNOWN
Classifier: License :: OSI Approved :: Apache Software License
Classifier: Programming Language :: Python
Classifier: Programming Language :: Python :: 3
Classifier: Programming Language :: Python :: 3.7
Classifier: Programming Language :: Python :: 3.8
Classifier: Programming Language :: Python :: 3.9
Requires-Python: >=3.7.0
License-File: LICENSE
Requires-Dist: numpy (<2,>=1.21.0)
Requires-Dist: scipy (<2,>=1.7.0)
Requires-Dist: pandas (<2,>=1.2.5)
Requires-Dist: matplotlib (<4,>=3.4.2)
Requires-Dist: scikit-learn (<0.25,>=0.24.0)
Provides-Extra: lolo
Requires-Dist: lolopy (<2,>=1.2.0) ; extra == 'lolo'
Requires-Dist: py4j (<0.11,>=0.10.9) ; extra == 'lolo'
Provides-Extra: optional
Requires-Dist: py4j (<0.11,>=0.10.9) ; extra == 'optional'
Requires-Dist: pymatgen (>=2022.0.9) ; extra == 'optional'
Requires-Dist: matminer (<0.8,>=0.7.3) ; extra == 'optional'
